README.md
license.txt
setup.py
strategy_analytics/__init__.py
strategy_analytics/strategy_tearsheet.py
strategy_analytics.egg-info/PKG-INFO
strategy_analytics.egg-info/SOURCES.txt
strategy_analytics.egg-info/dependency_links.txt
strategy_analytics.egg-info/top_level.txt