Metadata-Version: 2.1
Name: strategy-analytics
Version: 0.0.0.2
Summary: A library to produce strategy analytics
Author: QuantInsti
License: MIT
Platform: UNKNOWN
License-File: license.txt
